__init__.py
agi_env/__init__.py
agi_env/agi_env.py
agi_env/agi_logger.py
agi_env/app_args.py
agi_env/defaults.py
agi_env/pagelib.py
agi_env/streamlit_args.py
agi_env/resources/.DS_Store
agi_env/resources/.agilab/.env
agi_env/resources/.agilab/balancer_df.csv
agi_env/resources/.agilab/balancer_model.pkl
agi_env/resources/mistral_offline/.DS_Store
agi_env/resources/mistral_offline/README.md
agi_env/resources/mistral_offline/data/.gitignore
agi_env/resources/mistral_offline/data/.gitkeep
agi_env-2025.12.19.data/data/agi_env/pyproject.toml
agi_env-2025.12.19.data/data/agi_env/uv_config.toml
agi_env-2025.12.19.dist-info/licenses/LICENSE
agi_env-2025.12.19.dist-info/METADATA
agi_env-2025.12.19.dist-info/WHEEL
agi_env-2025.12.19.dist-info/top_level.txt
agi_env-2025.12.19.dist-info/RECORD
