Metadata-Version: 2.4
Name: agi-env
Version: 2025.12.19
Summary: AGI Env
Author-email: Jean-Pierre Morard <focus@thalesgroup.com>
Project-URL: Documentation, https://thalesgroup.github.io/agilab
Project-URL: Source, https://github.com/ThalesGroup/agilab/tree/main/src/agilab/agi-env
Project-URL: Tracker, https://github.com/ThalesGroup/agilab/issues
Keywords: jupyter,mlflow,asyncio,dask,rapids,streamlit,distributed,cython,cluster,dataframe,dataset,loadbalancing,genai,copilot,agi,pycharm,datascience
Classifier: Intended Audience :: Developers
Classifier: Development Status :: 3 - Alpha
Classifier: Programming Language :: Python :: 3
Classifier: Programming Language :: Python :: 3.11
Classifier: Programming Language :: Python :: 3.12
Classifier: Programming Language :: Python :: 3.13
Classifier: Operating System :: MacOS
Classifier: Operating System :: Microsoft :: Windows
Classifier: Operating System :: POSIX :: Linux
Requires-Python: >=3.11
License-File: LICENSE
Requires-Dist: humanize
Requires-Dist: pydantic
Requires-Dist: python-dotenv
Requires-Dist: setuptools
Requires-Dist: tomlkit
Requires-Dist: astor
Requires-Dist: psutil
Requires-Dist: pathspec
Requires-Dist: ipython
Requires-Dist: py7zr
Requires-Dist: cmake>=3.29
Requires-Dist: numba
Requires-Dist: streamlit
Dynamic: license-file
